macrocosmos_mcp/__init__.py
macrocosmos_mcp/macrocosmos_mcp.py
macrocosmos_mcp/macrocosmos_mcp_sse.py
macrocosmos_mcp-0.2.1.dist-info/METADATA
macrocosmos_mcp-0.2.1.dist-info/WHEEL
macrocosmos_mcp-0.2.1.dist-info/entry_points.txt
macrocosmos_mcp-0.2.1.dist-info/top_level.txt
macrocosmos_mcp-0.2.1.dist-info/RECORD
