Metadata-Version: 2.4
Name: macrocosmos-mcp
Version: 0.2.1
Summary: MCP server for integrating Macrocosmos SN13 social media data into Claude Desktop and Cursor
Author: Macrocosmos AI
License: MIT
Project-URL: Homepage, https://github.com/macrocosm-os/macrocosmos-mcp
Project-URL: Repository, https://github.com/macrocosm-os/macrocosmos-mcp
Keywords: mcp,claude,cursor,api,social-data,huggingface
Classifier: Development Status :: 3 - Alpha
Classifier: Intended Audience :: Developers
Classifier: License :: OSI Approved :: MIT License
Classifier: Programming Language :: Python :: 3
Classifier: Programming Language :: Python :: 3.10
Classifier: Programming Language :: Python :: 3.11
Classifier: Programming Language :: Python :: 3.12
Requires-Python: <3.13,>=3.10
Requires-Dist: mcp[cli]
Requires-Dist: httpx
Requires-Dist: macrocosmos
Provides-Extra: dev
Requires-Dist: pytest; extra == "dev"
Requires-Dist: pytest-asyncio; extra == "dev"
Requires-Dist: ruff; extra == "dev"
Requires-Dist: build; extra == "dev"
Requires-Dist: twine; extra == "dev"
